dart_hj3415/__init__.py
dart_hj3415/cli.py
dart_hj3415/opendart.py
dart_hj3415-2.3.4.dist-info/entry_points.txt
dart_hj3415-2.3.4.dist-info/WHEEL
dart_hj3415-2.3.4.dist-info/METADATA
dart_hj3415-2.3.4.dist-info/RECORD
