Metadata-Version: 2.3
Name: dart_hj3415
Version: 2.3.4
Summary: Save data from https://opendart.fss.or.kr
Author-email: Hyungjin Kim <hj3415@gmail.com>
Classifier: License :: OSI Approved :: MIT License
Requires-Dist: requests>=2.32.3
Requires-Dist: utils_hj3415>=3.2.0
Requires-Dist: webdriver-hj3415>=2.0.1
Requires-Dist: db_hj3415>=4.7.0
Project-URL: Home, https://www.hyungjin.kr
